InjecToast/ToastInjector.py
InjecToast/__init__.py
InjecToast/argparser.py
InjecToast-1.1.6.dist-info/METADATA
InjecToast-1.1.6.dist-info/WHEEL
InjecToast-1.1.6.dist-info/entry_points.txt
InjecToast-1.1.6.dist-info/top_level.txt
InjecToast-1.1.6.dist-info/RECORD
