Metadata-Version: 2.1
Name: InjecToast
Version: 1.1.6
Summary: A tool to inject toasts in Android applications.
Author-email: PatzEdi <edwardferrari717@gmail.com>
Project-URL: Homepage, https://github.com/PatzEdi
Project-URL: Repository, https://github.com/PatzEdi/InjecToast
Project-URL: Bug Tracker, https://github.com/PatzEdi/InjecToast/issues
Keywords: android,androidtool,reverse-engineering,development
Classifier: Programming Language :: Python :: 3
Classifier: License :: OSI Approved :: MIT License
Classifier: Operating System :: OS Independent
Requires-Python: >=3.9
